{
  "ComponentAllowCustomization": true,
  "ComponentChangedSinceFileImport": true,
  "ComponentDefinitionInfo": {
    "AllowAccessToGlobals": false,
    "Children": [
      {
        "AllowAccessToGlobals": true,
        "Children": [],
        "ControlPropertyState": [
          {
            "AFDDataSourceName": "",
            "AutoRuleBindingEnabled": false,
            "AutoRuleBindingString": "",
            "InvariantPropertyName": "Fill",
            "IsLockable": false,
            "NameMapSourceSchema": "?"
          },
          "DisabledFill",
          "PressedFill",
          "HoverFill",
          {
            "AFDDataSourceName": "",
            "AutoRuleBindingEnabled": false,
            "AutoRuleBindingString": "",
            "InvariantPropertyName": "BorderColor",
            "IsLockable": false,
            "NameMapSourceSchema": "?"
          },
          "BorderStyle",
          "FocusedBorderColor",
          "DisplayMode",
          "X",
          "Y",
          "Width",
          {
            "AFDDataSourceName": "",
            "AutoRuleBindingEnabled": false,
            "AutoRuleBindingString": "",
            "InvariantPropertyName": "Height",
            "IsLockable": false,
            "NameMapSourceSchema": "?"
          },
          "ZIndex",
          "Visible",
          "ContentLanguage"
        ],
        "ControlUniqueId": "5",
        "HasDynamicProperties": false,
        "Index": 0,
        "IsAutoGenerated": false,
        "IsDataControl": false,
        "IsFromScreenLayout": true,
        "IsGroupControl": false,
        "IsLocked": false,
        "LayoutName": "",
        "MetaDataIDKey": "",
        "Name": "RectQuickActionBar",
        "Parent": "CmpntHeader",
        "PersistMetaDataIDKey": false,
        "PublishOrderIndex": 332,
        "Rules": [
          {
            "Category": "Data",
            "InvariantScript": "\"\"",
            "Property": "ContentLanguage",
            "RuleProviderType": "Unknown"
          },
          {
            "Category": "Design",
            "InvariantScript": "RGBA(255, 255, 0, 1)",
            "Property": "BorderColor",
            "RuleProviderType": "Unknown"
          },
          {
            "Category": "Design",
            "InvariantScript": "Self.Fill",
            "Property": "PressedFill",
            "RuleProviderType": "Unknown"
          },
          {
            "Category": "Design",
            "InvariantScript": "Self.Fill",
            "Property": "DisabledFill",
            "RuleProviderType": "Unknown"
          },
          {
            "Category": "Design",
            "InvariantScript": "Self.BorderColor",
            "Property": "FocusedBorderColor",
            "RuleProviderType": "Unknown"
          },
          {
            "Category": "Design",
            "InvariantScript": "BorderStyle.Solid",
            "Property": "BorderStyle",
            "RuleProviderType": "Unknown"
          },
          {
            "Category": "Design",
            "InvariantScript": "DisplayMode.Edit",
            "Property": "DisplayMode",
            "RuleProviderType": "Unknown"
          },
          {
            "Category": "Design",
            "InvariantScript": "RGBA(254, 209, 46, 1)",
            "Property": "Fill",
            "RuleProviderType": "Unknown"
          },
          {
            "Category": "Design",
            "InvariantScript": "0",
            "Property": "X",
            "RuleProviderType": "Unknown"
          },
          {
            "Category": "Design",
            "InvariantScript": "0",
            "Property": "Y",
            "RuleProviderType": "Unknown"
          },
          {
            "Category": "Design",
            "InvariantScript": "Parent.Width",
            "Property": "Width",
            "RuleProviderType": "Unknown"
          },
          {
            "Category": "Design",
            "InvariantScript": "true",
            "Property": "Visible",
            "RuleProviderType": "Unknown"
          },
          {
            "Category": "Design",
            "InvariantScript": "1",
            "Property": "ZIndex",
            "RuleProviderType": "Unknown"
          },
          {
            "Category": "Design",
            "InvariantScript": "30",
            "Property": "Height",
            "RuleProviderType": "Unknown"
          },
          {
            "Category": "Design",
            "InvariantScript": "Self.Fill",
            "Property": "HoverFill",
            "RuleProviderType": "Unknown"
          }
        ],
        "StyleName": "invertedBackgroundRectangleStyle",
        "Template": {
          "CustomGroupControlTemplateName": "",
          "FirstParty": true,
          "Id": "http://microsoft.com/appmagic/shapes/rectangle",
          "IsComponentDefinition": false,
          "IsCustomGroupControlTemplate": false,
          "IsPremiumPcfControl": false,
          "LastModifiedTimestamp": "0",
          "Name": "rectangle",
          "OverridableProperties": {},
          "Version": "2.3.0"
        },
        "Type": "ControlInfo",
        "VariantName": ""
      },
      {
        "AllowAccessToGlobals": true,
        "Children": [],
        "ControlPropertyState": [
          "Live",
          "Overflow",
          {
            "AFDDataSourceName": "",
            "AutoRuleBindingEnabled": false,
            "AutoRuleBindingString": "\"Text\"",
            "InvariantPropertyName": "Text",
            "IsLockable": false,
            "NameMapSourceSchema": "?"
          },
          "Role",
          {
            "AFDDataSourceName": "",
            "AutoRuleBindingEnabled": false,
            "AutoRuleBindingString": "RGBA(51, 51, 51, 1)",
            "InvariantPropertyName": "Color",
            "IsLockable": false,
            "NameMapSourceSchema": "?"
          },
          "DisabledColor",
          "PressedColor",
          "HoverColor",
          "BorderColor",
          "DisabledBorderColor",
          "PressedBorderColor",
          "HoverBorderColor",
          "BorderStyle",
          "FocusedBorderColor",
          "Fill",
          "DisabledFill",
          "PressedFill",
          "HoverFill",
          {
            "AFDDataSourceName": "",
            "AutoRuleBindingEnabled": false,
            "AutoRuleBindingString": "",
            "InvariantPropertyName": "Font",
            "IsLockable": false,
            "NameMapSourceSchema": "?"
          },
          {
            "AFDDataSourceName": "",
            "AutoRuleBindingEnabled": false,
            "AutoRuleBindingString": "",
            "InvariantPropertyName": "FontWeight",
            "IsLockable": false,
            "NameMapSourceSchema": "?"
          },
          {
            "AFDDataSourceName": "",
            "AutoRuleBindingEnabled": false,
            "AutoRuleBindingString": "",
            "InvariantPropertyName": "Align",
            "IsLockable": false,
            "NameMapSourceSchema": "?"
          },
          {
            "AFDDataSourceName": "",
            "AutoRuleBindingEnabled": false,
            "AutoRuleBindingString": "",
            "InvariantPropertyName": "VerticalAlign",
            "IsLockable": false,
            "NameMapSourceSchema": "?"
          },
          "X",
          "Y",
          {
            "AFDDataSourceName": "",
            "AutoRuleBindingEnabled": false,
            "AutoRuleBindingString": "",
            "InvariantPropertyName": "Width",
            "IsLockable": false,
            "NameMapSourceSchema": "?"
          },
          {
            "AFDDataSourceName": "",
            "AutoRuleBindingEnabled": false,
            "AutoRuleBindingString": "",
            "InvariantPropertyName": "Height",
            "IsLockable": false,
            "NameMapSourceSchema": "?"
          },
          "DisplayMode",
          "ZIndex",
          "LineHeight",
          "BorderThickness",
          "FocusedBorderThickness",
          {
            "AFDDataSourceName": "",
            "AutoRuleBindingEnabled": false,
            "AutoRuleBindingString": "",
            "InvariantPropertyName": "Size",
            "IsLockable": false,
            "NameMapSourceSchema": "?"
          },
          "Italic",
          "Underline",
          "Strikethrough",
          {
            "AFDDataSourceName": "",
            "AutoRuleBindingEnabled": false,
            "AutoRuleBindingString": "",
            "InvariantPropertyName": "PaddingTop",
            "IsLockable": false,
            "NameMapSourceSchema": "?"
          },
          "PaddingRight",
          "PaddingBottom",
          {
            "AFDDataSourceName": "",
            "AutoRuleBindingEnabled": false,
            "AutoRuleBindingString": "",
            "InvariantPropertyName": "PaddingLeft",
            "IsLockable": false,
            "NameMapSourceSchema": "?"
          },
          "ContentLanguage"
        ],
        "ControlUniqueId": "6",
        "HasDynamicProperties": false,
        "Index": 0,
        "IsAutoGenerated": false,
        "IsDataControl": false,
        "IsFromScreenLayout": false,
        "IsGroupControl": false,
        "IsLocked": false,
        "LayoutName": "",
        "MetaDataIDKey": "",
        "Name": "LblHeader",
        "Parent": "CmpntHeader",
        "PersistMetaDataIDKey": false,
        "PublishOrderIndex": 333,
        "Rules": [
          {
            "Category": "Data",
            "InvariantScript": "TextRole.Default",
            "Property": "Role",
            "RuleProviderType": "Unknown"
          },
          {
            "Category": "Data",
            "InvariantScript": "CmpntHeader.HeaderText",
            "Property": "Text",
            "RuleProviderType": "Unknown"
          },
          {
            "Category": "Data",
            "InvariantScript": "Live.Off",
            "Property": "Live",
            "RuleProviderType": "Unknown"
          },
          {
            "Category": "Data",
            "InvariantScript": "\"\"",
            "Property": "ContentLanguage",
            "RuleProviderType": "Unknown"
          },
          {
            "Category": "Design",
            "InvariantScript": "18",
            "Property": "Size",
            "RuleProviderType": "Unknown"
          },
          {
            "Category": "Design",
            "InvariantScript": "4",
            "Property": "FocusedBorderThickness",
            "RuleProviderType": "Unknown"
          },
          {
            "Category": "Design",
            "InvariantScript": "2",
            "Property": "BorderThickness",
            "RuleProviderType": "Unknown"
          },
          {
            "Category": "Design",
            "InvariantScript": "1.2",
            "Property": "LineHeight",
            "RuleProviderType": "Unknown"
          },
          {
            "Category": "Design",
            "InvariantScript": "2",
            "Property": "ZIndex",
            "RuleProviderType": "Unknown"
          },
          {
            "Category": "Design",
            "InvariantScript": "DisplayMode.Edit",
            "Property": "DisplayMode",
            "RuleProviderType": "Unknown"
          },
          {
            "Category": "Design",
            "InvariantScript": "100",
            "Property": "PaddingLeft",
            "RuleProviderType": "Unknown"
          },
          {
            "Category": "Design",
            "InvariantScript": "5",
            "Property": "PaddingBottom",
            "RuleProviderType": "Unknown"
          },
          {
            "Category": "Design",
            "InvariantScript": "30",
            "Property": "Height",
            "RuleProviderType": "Unknown"
          },
          {
            "Category": "Design",
            "InvariantScript": "1366",
            "Property": "Width",
            "RuleProviderType": "Unknown"
          },
          {
            "Category": "Design",
            "InvariantScript": "5",
            "Property": "PaddingRight",
            "RuleProviderType": "Unknown"
          },
          {
            "Category": "Design",
            "InvariantScript": "3",
            "Property": "PaddingTop",
            "RuleProviderType": "Unknown"
          },
          {
            "Category": "Design",
            "InvariantScript": "0",
            "Property": "Y",
            "RuleProviderType": "Unknown"
          },
          {
            "Category": "Design",
            "InvariantScript": "false",
            "Property": "Strikethrough",
            "RuleProviderType": "Unknown"
          },
          {
            "Category": "Design",
            "InvariantScript": "0",
            "Property": "X",
            "RuleProviderType": "Unknown"
          },
          {
            "Category": "Design",
            "InvariantScript": "VerticalAlign.Middle",
            "Property": "VerticalAlign",
            "RuleProviderType": "Unknown"
          },
          {
            "Category": "Design",
            "InvariantScript": "false",
            "Property": "Underline",
            "RuleProviderType": "Unknown"
          },
          {
            "Category": "Design",
            "InvariantScript": "false",
            "Property": "Italic",
            "RuleProviderType": "Unknown"
          },
          {
            "Category": "Design",
            "InvariantScript": "Align.Justify",
            "Property": "Align",
            "RuleProviderType": "Unknown"
          },
          {
            "Category": "Design",
            "InvariantScript": "FontWeight.Bold",
            "Property": "FontWeight",
            "RuleProviderType": "Unknown"
          },
          {
            "Category": "Design",
            "InvariantScript": "Font.Arial",
            "Property": "Font",
            "RuleProviderType": "Unknown"
          },
          {
            "Category": "Design",
            "InvariantScript": "RGBA(0, 0, 0, 0)",
            "Property": "DisabledFill",
            "RuleProviderType": "Unknown"
          },
          {
            "Category": "Design",
            "InvariantScript": "RGBA(0, 0, 0, 0)",
            "Property": "Fill",
            "RuleProviderType": "Unknown"
          },
          {
            "Category": "Design",
            "InvariantScript": "BorderStyle.None",
            "Property": "BorderStyle",
            "RuleProviderType": "Unknown"
          },
          {
            "Category": "Design",
            "InvariantScript": "RGBA(0, 0, 0, 0)",
            "Property": "DisabledBorderColor",
            "RuleProviderType": "Unknown"
          },
          {
            "Category": "Design",
            "InvariantScript": "RGBA(0, 0, 0, 0)",
            "Property": "BorderColor",
            "RuleProviderType": "Unknown"
          },
          {
            "Category": "Design",
            "InvariantScript": "RGBA(166, 166, 166, 1)",
            "Property": "DisabledColor",
            "RuleProviderType": "Unknown"
          },
          {
            "Category": "Design",
            "InvariantScript": "RGBA(255, 255, 255, 1)",
            "Property": "Color",
            "RuleProviderType": "Unknown"
          },
          {
            "Category": "Design",
            "InvariantScript": "Overflow.Hidden",
            "Property": "Overflow",
            "RuleProviderType": "Unknown"
          },
          {
            "Category": "Design",
            "InvariantScript": "Self.Fill",
            "Property": "HoverFill",
            "RuleProviderType": "Unknown"
          },
          {
            "Category": "Design",
            "InvariantScript": "Self.Fill",
            "Property": "PressedFill",
            "RuleProviderType": "Unknown"
          },
          {
            "Category": "Design",
            "InvariantScript": "Self.BorderColor",
            "Property": "FocusedBorderColor",
            "RuleProviderType": "Unknown"
          },
          {
            "Category": "Design",
            "InvariantScript": "Self.BorderColor",
            "Property": "HoverBorderColor",
            "RuleProviderType": "Unknown"
          },
          {
            "Category": "Design",
            "InvariantScript": "Self.BorderColor",
            "Property": "PressedBorderColor",
            "RuleProviderType": "Unknown"
          },
          {
            "Category": "Design",
            "InvariantScript": "Self.Color",
            "Property": "HoverColor",
            "RuleProviderType": "Unknown"
          },
          {
            "Category": "Design",
            "InvariantScript": "Self.Color",
            "Property": "PressedColor",
            "RuleProviderType": "Unknown"
          }
        ],
        "StyleName": "defaultLabelStyle",
        "Template": {
          "CustomGroupControlTemplateName": "",
          "FirstParty": true,
          "Id": "http://microsoft.com/appmagic/label",
          "IsComponentDefinition": false,
          "IsCustomGroupControlTemplate": false,
          "IsPremiumPcfControl": false,
          "LastModifiedTimestamp": "0",
          "Name": "label",
          "OverridableProperties": {},
          "Version": "2.5.1"
        },
        "Type": "ControlInfo",
        "VariantName": ""
      },
      {
        "AllowAccessToGlobals": true,
        "Children": [],
        "ControlPropertyState": [
          {
            "AFDDataSourceName": "",
            "AutoRuleBindingEnabled": false,
            "AutoRuleBindingString": "",
            "InvariantPropertyName": "Icon",
            "IsLockable": false,
            "NameMapSourceSchema": "?"
          },
          {
            "AFDDataSourceName": "",
            "AutoRuleBindingEnabled": false,
            "AutoRuleBindingString": "",
            "InvariantPropertyName": "Color",
            "IsLockable": false,
            "NameMapSourceSchema": "?"
          },
          "DisabledColor",
          "PressedColor",
          {
            "AFDDataSourceName": "",
            "AutoRuleBindingEnabled": false,
            "AutoRuleBindingString": "ColorFade(RGBA(105, 121, 126, 1), -30%)",
            "InvariantPropertyName": "HoverColor",
            "IsLockable": false,
            "NameMapSourceSchema": "?"
          },
          "Fill",
          "DisabledFill",
          "PressedFill",
          "HoverFill",
          "DisplayMode",
          "X",
          "Y",
          "Width",
          "Height",
          "BorderStyle",
          "BorderColor",
          "DisabledBorderColor",
          "PressedBorderColor",
          "HoverBorderColor",
          "FocusedBorderColor",
          "ZIndex",
          "BorderThickness",
          "FocusedBorderThickness",
          {
            "AFDDataSourceName": "",
            "AutoRuleBindingEnabled": false,
            "AutoRuleBindingString": "false",
            "InvariantPropertyName": "OnSelect",
            "IsLockable": false,
            "NameMapSourceSchema": "?"
          },
          {
            "AFDDataSourceName": "",
            "AutoRuleBindingEnabled": false,
            "AutoRuleBindingString": "true",
            "InvariantPropertyName": "Visible",
            "IsLockable": false,
            "NameMapSourceSchema": "?"
          },
          "ContentLanguage"
        ],
        "ControlUniqueId": "7",
        "HasDynamicProperties": false,
        "Index": 0,
        "IsAutoGenerated": false,
        "IsDataControl": false,
        "IsFromScreenLayout": false,
        "IsGroupControl": false,
        "IsLocked": false,
        "LayoutName": "",
        "MetaDataIDKey": "",
        "Name": "IcnHome",
        "Parent": "CmpntHeader",
        "PersistMetaDataIDKey": false,
        "PublishOrderIndex": 334,
        "Rules": [
          {
            "Category": "Data",
            "InvariantScript": "\"\"",
            "Property": "ContentLanguage",
            "RuleProviderType": "Unknown"
          },
          {
            "Category": "Design",
            "InvariantScript": "4",
            "Property": "FocusedBorderThickness",
            "RuleProviderType": "Unknown"
          },
          {
            "Category": "Design",
            "InvariantScript": "0",
            "Property": "BorderThickness",
            "RuleProviderType": "Unknown"
          },
          {
            "Category": "Design",
            "InvariantScript": "3",
            "Property": "ZIndex",
            "RuleProviderType": "Unknown"
          },
          {
            "Category": "Design",
            "InvariantScript": "RGBA(0, 0, 0, 0)",
            "Property": "HoverBorderColor",
            "RuleProviderType": "Unknown"
          },
          {
            "Category": "Design",
            "InvariantScript": "RGBA(0, 0, 0, 0)",
            "Property": "PressedBorderColor",
            "RuleProviderType": "Unknown"
          },
          {
            "Category": "Design",
            "InvariantScript": "RGBA(0, 0, 0, 0)",
            "Property": "DisabledBorderColor",
            "RuleProviderType": "Unknown"
          },
          {
            "Category": "Design",
            "InvariantScript": "RGBA(166, 166, 166, 1)",
            "Property": "BorderColor",
            "RuleProviderType": "Unknown"
          },
          {
            "Category": "Design",
            "InvariantScript": "BorderStyle.Solid",
            "Property": "BorderStyle",
            "RuleProviderType": "Unknown"
          },
          {
            "Category": "Design",
            "InvariantScript": "30",
            "Property": "Height",
            "RuleProviderType": "Unknown"
          },
          {
            "Category": "Design",
            "InvariantScript": "44",
            "Property": "Width",
            "RuleProviderType": "Unknown"
          },
          {
            "Category": "Design",
            "InvariantScript": "0",
            "Property": "Y",
            "RuleProviderType": "Unknown"
          },
          {
            "Category": "Design",
            "InvariantScript": "19",
            "Property": "X",
            "RuleProviderType": "Unknown"
          },
          {
            "Category": "Design",
            "InvariantScript": "DisplayMode.Edit",
            "Property": "DisplayMode",
            "RuleProviderType": "Unknown"
          },
          {
            "Category": "Design",
            "InvariantScript": "RGBA(0, 0, 0, 0)",
            "Property": "HoverFill",
            "RuleProviderType": "Unknown"
          },
          {
            "Category": "Design",
            "InvariantScript": "RGBA(0, 0, 0, 0)",
            "Property": "PressedFill",
            "RuleProviderType": "Unknown"
          },
          {
            "Category": "Design",
            "InvariantScript": "RGBA(0, 0, 0, 0)",
            "Property": "DisabledFill",
            "RuleProviderType": "Unknown"
          },
          {
            "Category": "Design",
            "InvariantScript": "RGBA(0, 0, 0, 0)",
            "Property": "Fill",
            "RuleProviderType": "Unknown"
          },
          {
            "Category": "Design",
            "InvariantScript": "ColorFade(RGBA(0, 0, 0 , 1), -30%)",
            "Property": "HoverColor",
            "RuleProviderType": "Unknown"
          },
          {
            "Category": "Design",
            "InvariantScript": "ColorFade(RGBA(105, 121, 126, 1), -30%)",
            "Property": "PressedColor",
            "RuleProviderType": "Unknown"
          },
          {
            "Category": "Design",
            "InvariantScript": "RGBA(220, 220, 220, 1)",
            "Property": "DisabledColor",
            "RuleProviderType": "Unknown"
          },
          {
            "Category": "Design",
            "InvariantScript": "RGBA(255, 255, 255, 1)",
            "Property": "Color",
            "RuleProviderType": "Unknown"
          },
          {
            "Category": "Design",
            "InvariantScript": "Icon.BackArrow",
            "Property": "Icon",
            "RuleProviderType": "Unknown"
          },
          {
            "Category": "Design",
            "InvariantScript": "Self.BorderColor",
            "Property": "FocusedBorderColor",
            "RuleProviderType": "Unknown"
          },
          {
            "Category": "Design",
            "InvariantScript": "CmpntHeader.ShowIcon",
            "Property": "Visible",
            "RuleProviderType": "Unknown"
          },
          {
            "Category": "Behavior",
            "InvariantScript": "Navigate(CmpntHeader.HomeNavigation, ScreenTransition.Fade)",
            "Property": "OnSelect",
            "RuleProviderType": "Unknown"
          }
        ],
        "StyleName": "defaultIconStyle",
        "Template": {
          "CustomGroupControlTemplateName": "",
          "FirstParty": true,
          "Id": "http://microsoft.com/appmagic/icon",
          "IsComponentDefinition": false,
          "IsCustomGroupControlTemplate": false,
          "IsPremiumPcfControl": false,
          "LastModifiedTimestamp": "0",
          "Name": "icon",
          "OverridableProperties": {},
          "Version": "2.5.0"
        },
        "Type": "ControlInfo",
        "VariantName": "Home"
      }
    ],
    "ControlPropertyState": [
      "Fill",
      {
        "AFDDataSourceName": "",
        "AutoRuleBindingEnabled": false,
        "AutoRuleBindingString": "",
        "InvariantPropertyName": "Height",
        "IsLockable": false,
        "NameMapSourceSchema": "?"
      },
      {
        "AFDDataSourceName": "",
        "AutoRuleBindingEnabled": false,
        "AutoRuleBindingString": "",
        "InvariantPropertyName": "Width",
        "IsLockable": false,
        "NameMapSourceSchema": "?"
      },
      "X",
      "Y",
      "ZIndex",
      "HeaderText",
      "HomeNavigation",
      "ShowIcon"
    ],
    "LastModifiedTimestamp": "638204980060335029",
    "Name": "CmpntHeader",
    "Rules": [
      {
        "Category": "Data",
        "InvariantScript": "\"Text\"",
        "Property": "HeaderText",
        "RuleProviderType": "System"
      },
      {
        "Category": "Data",
        "InvariantScript": "App.ActiveScreen",
        "Property": "HomeNavigation",
        "RuleProviderType": "System"
      },
      {
        "Category": "Data",
        "InvariantScript": "true",
        "Property": "ShowIcon",
        "RuleProviderType": "System"
      },
      {
        "Category": "Design",
        "InvariantScript": "1",
        "Property": "ZIndex",
        "RuleProviderType": "Unknown"
      },
      {
        "Category": "Design",
        "InvariantScript": "0",
        "Property": "Y",
        "RuleProviderType": "Unknown"
      },
      {
        "Category": "Design",
        "InvariantScript": "0",
        "Property": "X",
        "RuleProviderType": "Unknown"
      },
      {
        "Category": "Design",
        "InvariantScript": "1366",
        "Property": "Width",
        "RuleProviderType": "Unknown"
      },
      {
        "Category": "Design",
        "InvariantScript": "30",
        "Property": "Height",
        "RuleProviderType": "Unknown"
      },
      {
        "Category": "Design",
        "InvariantScript": "RGBA(0, 0, 0, 0)",
        "Property": "Fill",
        "RuleProviderType": "System"
      }
    ]
  },
  "ComponentManifest": {
    "AllowAccessToGlobals": false,
    "AllowCustomization": true,
    "Description": "",
    "Name": "CmpntHeader",
    "TemplateGuid": "30619f4d3f9a44b5b3f66f3f42b3c848"
  },
  "ComponentType": "CanvasComponent",
  "CustomGroupControlTemplateName": "",
  "CustomProperties": [
    {
      "Category": 0,
      "DisplayName": "Header Text",
      "Hidden": false,
      "Name": "HeaderText",
      "PropertyDataTypeKey": "String",
      "Tooltip": "A custom property",
      "Type": "{\"Version\":\"1.331\",\"Type\":{\"Name\":\"Root\",\"Kind\":\"String\",\"EnumString\":\"\",\"Type\":[]}}"
    },
    {
      "Category": 0,
      "DisplayName": "Home Navigation",
      "Hidden": false,
      "Name": "HomeNavigation",
      "PropertyDataTypeKey": "Screen",
      "Tooltip": "A custom property",
      "Type": "{\"Version\":\"1.331\",\"Type\":{\"Name\":\"Root\",\"Kind\":\"_LimPrimitive\",\"EnumString\":\"\",\"Template\":{\"TemplateName\":\"screen\",\"IsMetaLoc\":false,\"Intangible\":false,\"IsDataLimited\":false,\"ExpandoType\":{\"Version\":\"1.331\",\"Type\":{\"Name\":\"Root\",\"Kind\":\"Record\",\"EnumString\":\"\",\"Type\":[{\"Name\":\"BackgroundImage\",\"Kind\":\"Image\",\"EnumString\":\"\",\"Type\":[]},{\"Name\":\"ContentLanguage\",\"Kind\":\"String\",\"EnumString\":\"\",\"Type\":[]},{\"Name\":\"Fill\",\"Kind\":\"Color\",\"EnumString\":\"\",\"Type\":[]},{\"Name\":\"Height\",\"Kind\":\"Number\",\"EnumString\":\"\",\"Type\":[]},{\"Name\":\"ImagePosition\",\"Kind\":\"Enum\",\"EnumString\":\"%s[Center:\\\"center\\\", Fill:\\\"fill\\\", Fit:\\\"fit\\\", Stretch:\\\"stretch\\\", Tile:\\\"tile\\\"]\",\"Type\":[{\"Name\":\"Center\",\"Kind\":\"String\",\"EnumString\":\"\",\"Type\":[]},{\"Name\":\"Fill\",\"Kind\":\"String\",\"EnumString\":\"\",\"Type\":[]},{\"Name\":\"Fit\",\"Kind\":\"String\",\"EnumString\":\"\",\"Type\":[]},{\"Name\":\"Stretch\",\"Kind\":\"String\",\"EnumString\":\"\",\"Type\":[]},{\"Name\":\"Tile\",\"Kind\":\"String\",\"EnumString\":\"\",\"Type\":[]}]},{\"Name\":\"LoadingSpinner\",\"Kind\":\"Enum\",\"EnumString\":\"%n[Controls:0, Data:1, None:2]\",\"Type\":[{\"Name\":\"Controls\",\"Kind\":\"Number\",\"EnumString\":\"\",\"Type\":[]},{\"Name\":\"Data\",\"Kind\":\"Number\",\"EnumString\":\"\",\"Type\":[]},{\"Name\":\"None\",\"Kind\":\"Number\",\"EnumString\":\"\",\"Type\":[]}]},{\"Name\":\"LoadingSpinnerColor\",\"Kind\":\"Color\",\"EnumString\":\"\",\"Type\":[]},{\"Name\":\"Name\",\"Kind\":\"String\",\"EnumString\":\"\",\"Type\":[]},{\"Name\":\"Orientation\",\"Kind\":\"String\",\"EnumString\":\"\",\"Type\":[]},{\"Name\":\"Printing\",\"Kind\":\"Boolean\",\"EnumString\":\"\",\"Type\":[]},{\"Name\":\"Size\",\"Kind\":\"Number\",\"EnumString\":\"\",\"Type\":[]},{\"Name\":\"Width\",\"Kind\":\"Number\",\"EnumString\":\"\",\"Type\":[]}]}},\"Properties\":[{\"Name\":\"Fill\",\"InvariantType\":{\"Version\":\"1.331\",\"Type\":{\"Name\":\"Root\",\"Kind\":\"Color\",\"EnumString\":\"\",\"Type\":[]}},\"PropertyRuleCategory\":\"Design\",\"PropertyDisplayName\":\"Fill\"},{\"Name\":\"BackgroundImage\",\"InvariantType\":{\"Version\":\"1.331\",\"Type\":{\"Name\":\"Root\",\"Kind\":\"Image\",\"EnumString\":\"\",\"Type\":[]}},\"PropertyRuleCategory\":\"Data\",\"PropertyDisplayName\":\"Background image\"},{\"Name\":\"ImagePosition\",\"InvariantType\":{\"Version\":\"1.331\",\"Type\":{\"Name\":\"Root\",\"Kind\":\"Enum\",\"EnumString\":\"%s[Center:\\\"center\\\", Fill:\\\"fill\\\", Fit:\\\"fit\\\", Stretch:\\\"stretch\\\", Tile:\\\"tile\\\"]\",\"Type\":[{\"Name\":\"Center\",\"Kind\":\"String\",\"EnumString\":\"\",\"Type\":[]},{\"Name\":\"Fill\",\"Kind\":\"String\",\"EnumString\":\"\",\"Type\":[]},{\"Name\":\"Fit\",\"Kind\":\"String\",\"EnumString\":\"\",\"Type\":[]},{\"Name\":\"Stretch\",\"Kind\":\"String\",\"EnumString\":\"\",\"Type\":[]},{\"Name\":\"Tile\",\"Kind\":\"String\",\"EnumString\":\"\",\"Type\":[]}]}},\"PropertyRuleCategory\":\"Design\",\"PropertyDisplayName\":\"Image position\"},{\"Name\":\"Height\",\"InvariantType\":{\"Version\":\"1.331\",\"Type\":{\"Name\":\"Root\",\"Kind\":\"Number\",\"EnumString\":\"\",\"Type\":[]}},\"PropertyRuleCategory\":\"Design\",\"PropertyDisplayName\":\"Height\"},{\"Name\":\"Width\",\"InvariantType\":{\"Version\":\"1.331\",\"Type\":{\"Name\":\"Root\",\"Kind\":\"Number\",\"EnumString\":\"\",\"Type\":[]}},\"PropertyRuleCategory\":\"Design\",\"PropertyDisplayName\":\"Width\"},{\"Name\":\"Size\",\"InvariantType\":{\"Version\":\"1.331\",\"Type\":{\"Name\":\"Root\",\"Kind\":\"Number\",\"EnumString\":\"\",\"Type\":[]}},\"PropertyRuleCategory\":\"Design\",\"PropertyDisplayName\":\"Size\"},{\"Name\":\"Orientation\",\"InvariantType\":{\"Version\":\"1.331\",\"Type\":{\"Name\":\"Root\",\"Kind\":\"String\",\"EnumString\":\"\",\"Type\":[]}},\"PropertyRuleCategory\":\"Design\",\"PropertyDisplayName\":\"Orientation\"},{\"Name\":\"LoadingSpinner\",\"InvariantType\":{\"Version\":\"1.331\",\"Type\":{\"Name\":\"Root\",\"Kind\":\"Enum\",\"EnumString\":\"%n[Controls:0, Data:1, None:2]\",\"Type\":[{\"Name\":\"Controls\",\"Kind\":\"Number\",\"EnumString\":\"\",\"Type\":[]},{\"Name\":\"Data\",\"Kind\":\"Number\",\"EnumString\":\"\",\"Type\":[]},{\"Name\":\"None\",\"Kind\":\"Number\",\"EnumString\":\"\",\"Type\":[]}]}},\"PropertyRuleCategory\":\"Design\",\"PropertyDisplayName\":\"Loading spinner\"},{\"Name\":\"LoadingSpinnerColor\",\"InvariantType\":{\"Version\":\"1.331\",\"Type\":{\"Name\":\"Root\",\"Kind\":\"Color\",\"EnumString\":\"\",\"Type\":[]}},\"PropertyRuleCategory\":\"Design\",\"PropertyDisplayName\":\"Loading spinner color\"},{\"Name\":\"Name\",\"InvariantType\":{\"Version\":\"1.331\",\"Type\":{\"Name\":\"Root\",\"Kind\":\"String\",\"EnumString\":\"\",\"Type\":[]}},\"PropertyRuleCategory\":\"Design\",\"PropertyDisplayName\":\"Name\"},{\"Name\":\"Printing\",\"InvariantType\":{\"Version\":\"1.331\",\"Type\":{\"Name\":\"Root\",\"Kind\":\"Boolean\",\"EnumString\":\"\",\"Type\":[]}},\"PropertyRuleCategory\":\"Data\",\"PropertyDisplayName\":\"Printing\"},{\"Name\":\"ContentLanguage\",\"InvariantType\":{\"Version\":\"1.331\",\"Type\":{\"Name\":\"Root\",\"Kind\":\"String\",\"EnumString\":\"\",\"Type\":[]}},\"PropertyRuleCategory\":\"Data\",\"PropertyDisplayName\":\"Content language\"}]}}}"
    },
    {
      "Category": 0,
      "DisplayName": "Show Icon",
      "Hidden": false,
      "Name": "ShowIcon",
      "PropertyDataTypeKey": "Boolean",
      "Tooltip": "A custom property",
      "Type": "{\"Version\":\"1.331\",\"Type\":{\"Name\":\"Root\",\"Kind\":\"Boolean\",\"EnumString\":\"\",\"Type\":[]}}"
    }
  ],
  "FirstParty": true,
  "Id": "http://microsoft.com/appmagic/Component",
  "IsComponentLocked": false,
  "IsComponentTemplate": true,
  "IsCustomGroupControlTemplate": false,
  "IsPcfControl": false,
  "IsPremiumPcfControl": false,
  "IsWidgetTemplate": false,
  "LastModifiedTimestamp": "638204980060335029",
  "Name": "30619f4d3f9a44b5b3f66f3f42b3c848",
  "OverridableProperties": {},
  "Version": "637708914324062125"
}